uihelper/__init__.py
uihelper/helpers/__init__.py
uihelper/helpers/draw_helper.py
uihelper/helpers/draw_helper_pyqtgraph.py
uihelper/helpers/uihelper.py
uihelper/resources/__init__.py
uihelper/resources/resources_fonts.py
uihelper/resources/resources_material_icons.py
uihelper/widgets/__init__.py
uihelper/widgets/image_view_widget.py
uihelper/widgets/pcl_view_widget.py
uihelper/widgets/property_editor_tree/__init__.py
uihelper/widgets/property_editor_tree/editor_factory.py
uihelper/widgets/property_editor_tree/property_model.py
uihelper/widgets/property_editor_tree/property_tree_widget.py
uihelper/widgets/property_editor_tree/property_tree_widget_item.py
uihelper-0.0.2.dist-info/LICENSE
uihelper-0.0.2.dist-info/METADATA
uihelper-0.0.2.dist-info/WHEEL
uihelper-0.0.2.dist-info/top_level.txt
uihelper-0.0.2.dist-info/RECORD
