Metadata-Version: 2.1
Name: uihelper
Version: 0.0.2
Summary: The helper for GUI using PySide6
Home-page: https://github.com/joedlopes/uihelper
Author: Joed Lopes da Silva
Author-email: joedlopes@github.com
Project-URL: Bug Tracker, https://github.com/joedlopes/uihelper/issues
Classifier: Programming Language :: Python :: 3
Classifier: License :: OSI Approved :: MIT License
Classifier: Operating System :: OS Independent
Requires-Python: >=3.8
License-File: LICENSE
Requires-Dist: pyside6
Requires-Dist: pydantic
Requires-Dist: pyqtgraph
Requires-Dist: pyopengl
Requires-Dist: numpy
